avioflow/libavutil.so.59.39.100
avioflow/libavfilter.so.10.4.100
avioflow/libavcodec.so.61.19.100
avioflow/libavdevice.so.61.3.100
avioflow/libswscale.so.8.3.100
avioflow/libavioflow.so
avioflow/libavformat.so.61.7.100
avioflow/libswresample.so.5.3.100
avioflow/__init__.py
avioflow/_avioflow.cpython-310-x86_64-linux-gnu.so
avioflow-0.1.7.dist-info/WHEEL
avioflow-0.1.7.dist-info/METADATA
avioflow-0.1.7.dist-info/RECORD
avioflow.libs/libdrm-b0291a67.so.2.4.0
